powergrid/__init__.py
powergrid/constants.py
powergrid/tso.py
powergrid/tso_finder.py
powergrid-0.2.1.dist-info/METADATA
powergrid-0.2.1.dist-info/WHEEL
powergrid-0.2.1.dist-info/licenses/LICENSE
powergrid-0.2.1.dist-info/RECORD
