Metadata-Version: 2.4
Name: powergrid
Version: 0.2.1
Summary: A high-performance lookup library for Transmission System Operators (TSOs)
Project-URL: Homepage, https://github.com/cameraink/powergrid
Project-URL: Repository, https://github.com/cameraink/powergrid
Author: Guillaume Dion
License: MIT License
License-File: LICENSE
Classifier: Development Status :: 4 - Beta
Classifier: Intended Audience :: Developers
Classifier: Programming Language :: Python :: 3
Classifier: Programming Language :: Python :: 3.10
Classifier: Programming Language :: Python :: 3.11
Classifier: Programming Language :: Python :: 3.12
Classifier: Programming Language :: Python :: 3.13
Requires-Python: >=3.10
Requires-Dist: jsonschema
